extra_context.py
extra_context-1.0.0.dist-info/LICENSE
extra_context-1.0.0.dist-info/METADATA
extra_context-1.0.0.dist-info/WHEEL
extra_context-1.0.0.dist-info/top_level.txt
extra_context-1.0.0.dist-info/RECORD
