Metadata-Version: 2.1
Name: extra-context
Version: 1.0.0
Summary: Add additional context to warnings and exceptions
Home-page: https://github.com/WanzenBug/extra-context-py
Author: Moritz "WanzenBug" Wanzenböck
Author-email: moritz.wanzenboeck@gmail.com
License: UNKNOWN
Project-URL: Bug Reports, https://github.com/WanzenBug/extra-context-py/issues
Project-URL: Source, https://github.com/WanzenBug/extra-context-py
Keywords: warnings exception context logging
Platform: UNKNOWN
Classifier: Development Status :: 4 - Beta
Classifier: Intended Audience :: Developers
Classifier: Topic :: System :: Logging
Classifier: License :: OSI Approved :: MIT License
Classifier: Programming Language :: Python :: 2
Classifier: Programming Language :: Python :: 2.7
Classifier: Programming Language :: Python :: 3
Classifier: Programming Language :: Python :: 3.4
Classifier: Programming Language :: Python :: 3.5
Classifier: Programming Language :: Python :: 3.6
Classifier: Programming Language :: Python :: 3.7
Provides-Extra: test
Requires-Dist: pytest; extra == 'test'
